nobinobi_stats/__init__.py
nobinobi_stats/apps.py
nobinobi_stats/forms.py
nobinobi_stats/menus.py
nobinobi_stats/signals.py
nobinobi_stats/urls.py
nobinobi_stats/utils.py
nobinobi_stats/views.py
nobinobi_stats/locale/en/LC_MESSAGES/django.po
nobinobi_stats/locale/fr/LC_MESSAGES/django.mo
nobinobi_stats/locale/fr/LC_MESSAGES/django.po
nobinobi_stats/static/css/nobinobi_stats.css
nobinobi_stats/static/img/.gitignore
nobinobi_stats/static/js/nobinobi_stats.js
nobinobi_stats/templates/nobinobi_stats/attendance/attendance_calendar.html
nobinobi_stats/templates/nobinobi_stats/attendance/attendance_child.html
nobinobi_stats/templates/nobinobi_stats/attendance/attendance_period.html
nobinobi_stats/templates/nobinobi_stats/attendance/choice_attendance_calendar.html
nobinobi_stats/templates/nobinobi_stats/attendance/choice_attendance_child.html
nobinobi_stats/templates/nobinobi_stats/attendance/choice_attendance_period.html
nobinobi_stats/templates/nobinobi_stats/occupancy/choice_occupancy_period.html
nobinobi_stats/templates/nobinobi_stats/occupancy/occupancy_period.html
"nobinobi_stats/templatetags/__init__,py.py"
nobinobi_stats/templatetags/template_filters.py
nobinobi_stats/test_utils/__init__.py
nobinobi_stats/test_utils/test_app/__init__.py
nobinobi_stats/test_utils/test_app/admin.py
nobinobi_stats/test_utils/test_app/apps.py
nobinobi_stats/test_utils/test_app/models.py
nobinobi_stats/test_utils/test_app/migrations/__init__.py
nobinobi_stats-0.1.5.dist-info/AUTHORS.rst
nobinobi_stats-0.1.5.dist-info/LICENSE
nobinobi_stats-0.1.5.dist-info/METADATA
nobinobi_stats-0.1.5.dist-info/WHEEL
nobinobi_stats-0.1.5.dist-info/top_level.txt
nobinobi_stats-0.1.5.dist-info/RECORD
