Metadata-Version: 2.1
Name: nobinobi-stats
Version: 0.1.5
Summary: Application Stats for nobinobi
Home-page: https://github.com/prolibre-ch/nobinobi-stats
Author: Florian Alu
Author-email: alu@prolibre.com
Keywords: nobinobi-stats
Classifier: Development Status :: 4 - Beta
Classifier: Framework :: Django :: 3.2
Classifier: Intended Audience :: Developers
Classifier: License :: OSI Approved :: GNU Affero General Public License v3 or later (AGPLv3+)
Classifier: Natural Language :: English
Classifier: Programming Language :: Python :: 3
Classifier: Programming Language :: Python :: 3.6
Classifier: Programming Language :: Python :: 3.7
Classifier: Programming Language :: Python :: 3.8
License-File: LICENSE
License-File: AUTHORS.rst
Requires-Dist: drf-writable-nested (==0.6.3)
Requires-Dist: django-widget-tweaks (==1.4.8)
Requires-Dist: django-auto-one-to-one (==3.3.1)
Requires-Dist: nobinobi-daily-follow-up (==0.1.2)
